{"nodes":[{"color": "#c71969", "label": "backbone", "x": -134.2215, "y": -862.7517, "attributes": {}, "id": "backbone", "size": 6.1554675},{"color": "#c71969", "label": "underscore", "x": -75.53079, "y": -734.4221, "attributes": {}, "id": "underscore", "size": 100.0},{"color": "#c71969", "label": "requirejs", "x": 71.52897, "y": -612.5541, "attributes": {}, "id": "requirejs", "size": 4.0862627},{"color": "#c7b919", "label": "grunt", "x": 683.8534, "y": -710.3381, "attributes": {}, "id": "grunt", "size": 9.959153},{"color": "#c7b919", "label": "grunt-contrib-less", "x": -215.58498, "y": -611.3146, "attributes": {}, "id": "grunt-contrib-less", "size": 0.6173013},{"color": "#c7b919", "label": "grunt-contrib-jshint", "x": 548.61926, "y": -938.3397, "attributes": {}, "id": "grunt-contrib-jshint", "size": 1.3171794},{"color": "#c7b919", "label": "grunt-contrib-uglify", "x": 160.96982, "y": -871.8892, "attributes": {}, "id": "grunt-contrib-uglify", "size": 1.1346025},{"color": "#c79f19", "label": "npmlog", "x": 856.64276, "y": -713.69055, "attributes": {}, "id": "npmlog", "size": 1.4084679},{"color": "#c78419", "label": "coffee-script", "x": 81.49971, "y": -915.89026, "attributes": {}, "id": "coffee-script", "size": 44.131462},{"color": "#c78419", "label": "node-minify", "x": 284.06558, "y": -772.7816, "attributes": {}, "id": "node-minify", "size": 0.76944876},{"color": "#c7199f", "label": "underscorem", "x": -106.96772, "y": -865.8074, "attributes": {}, "id": "underscorem", "size": 0.6173013},{"color": "#c719b9", "label": "hubot", "x": -280.204, "y": -683.4332, "attributes": {}, "id": "hubot", "size": 1.165032},{"color": "#c78419", "label": "eco", "x": 61.016094, "y": -986.8328, "attributes": {}, "id": "eco", "size": 2.230064},{"color": "#c71919", "label": "coffeekup", "x": 85.66932, "y": -987.40234, "attributes": {}, "id": "coffeekup", "size": 0.55644226},{"color": "#c78419", "label": "uglify-js", "x": 177.18362, "y": -699.5852, "attributes": {}, "id": "uglify-js", "size": 22.252666},{"color": "#19b9c7", "label": "hashish", "x": 691.4775, "y": -983.94257, "attributes": {}, "id": "hashish", "size": 1.3780384},{"color": "#19c7b9", "label": "netmask", "x": 39.66092, "y": -974.2597, "attributes": {}, "id": "netmask", "size": 0.43472436},{"color": "#c78419", "label": "jshint", "x": 533.37573, "y": -839.91656, "attributes": {}, "id": "jshint", "size": 3.0212305},{"color": "#c7b919", "label": "grunt-lib-contrib", "x": -221.20235, "y": -830.87317, "attributes": {}, "id": "grunt-lib-contrib", "size": 1.8040513},{"color": "#19b9c7", "label": "sk", "x": 333.07233, "y": -781.8526, "attributes": {}, "id": "sk", "size": 0.58687174},{"color": "#c71919", "label": "cli", "x": 467.85532, "y": -816.1008, "attributes": {}, "id": "cli", "size": 2.047487},{"color": "#19c7b9", "label": "argparse", "x": 336.41046, "y": -633.0312, "attributes": {}, "id": "argparse", "size": 1.4388975},{"color": "#c79f19", "label": "shelljs", "x": 499.16705, "y": -900.85004, "attributes": {}, "id": "shelljs", "size": 3.234237},{"color": "#c78419", "label": "optparse", "x": -301.50488, "y": -843.711, "attributes": {}, "id": "optparse", "size": 1.0128845},{"color": "#19c719", "label": "charm", "x": 684.35016, "y": -855.05255, "attributes": {}, "id": "charm", "size": 1.1346025},{"color": "#c71919", "label": "swig", "x": -189.87314, "y": -807.8819, "attributes": {}, "id": "swig", "size": 1.6214744},{"color": "#19c769", "label": "resolve", "x": 695.9144, "y": -923.4041, "attributes": {}, "id": "resolve", "size": 1.6214744},{"color": "#c71919", "label": "jqtpl", "x": -155.0798, "y": -843.789, "attributes": {}, "id": "jqtpl", "size": 0.67816025},{"color": "#19b9c7", "label": "traverse", "x": 607.4505, "y": -869.6334, "attributes": {}, "id": "traverse", "size": 2.169205},{"color": "#c71969", "label": "natural", "x": -159.15141, "y": -906.51306, "attributes": {}, "id": "natural", "size": 0.7998782},{"color": "#9f19c7", "label": "printf", "x": 321.60583, "y": -842.82385, "attributes": {}, "id": "printf", "size": 0.52601284},{"color": "#9fc719", "label": "password-hash", "x": 94.21731, "y": -632.2503, "attributes": {}, "id": "password-hash", "size": 0.40429485},{"color": "#c78419", "label": "coffeecup", "x": -216.88039, "y": -872.26465, "attributes": {}, "id": "coffeecup", "size": 0.7390192},{"color": "#19c7b9", "label": "js-yaml", "x": 761.8784, "y": -631.6599, "attributes": {}, "id": "js-yaml", "size": 5.2121534},{"color": "#19c719", "label": "node-xml", "x": -311.38135, "y": -713.54456, "attributes": {}, "id": "node-xml", "size": 0.40429485},{"color": "#c78419", "label": "sqwish", "x": 393.27988, "y": -771.2408, "attributes": {}, "id": "sqwish", "size": 0.70858973},{"color": "#c71969", "label": "postal", "x": -171.42653, "y": -829.2972, "attributes": {}, "id": "postal", "size": 0.43472436},{"color": "#19c74f", "label": "sequence", "x": 365.48837, "y": -713.06415, "attributes": {}, "id": "sequence", "size": 0.43472436},{"color": "#c78419", "label": "node-log", "x": 393.26965, "y": -626.0221, "attributes": {}, "id": "node-log", "size": 0.4651538},{"color": "#c78419", "label": "burrito", "x": 397.68042, "y": -825.43256, "attributes": {}, "id": "burrito", "size": 0.67816025},{"color": "#c71969", "label": "sylvester", "x": -188.29977, "y": -948.5652, "attributes": {}, "id": "sylvester", "size": 0.43472436},{"color": "#c71969", "label": "JSONPath", "x": -202.30043, "y": -781.22864, "attributes": {}, "id": "JSONPath", "size": 0.58687174},{"color": "#c7b919", "label": "extended", "x": 657.08826, "y": -962.1278, "attributes": {}, "id": "extended", "size": 0.70858973},{"color": "#c7b919", "label": "array-extended", "x": 563.8498, "y": -995.6015, "attributes": {}, "id": "array-extended", "size": 0.6173013},{"color": "#19c7b9", "label": "smoosh", "x": 576.5164, "y": -627.7807, "attributes": {}, "id": "smoosh", "size": 0.55644226},{"color": "#19c719", "label": "difflet", "x": 666.7738, "y": -828.60913, "attributes": {}, "id": "difflet", "size": 0.52601284},{"color": "#c76919", "label": "yamljs", "x": 429.07022, "y": -625.1245, "attributes": {}, "id": "yamljs", "size": 0.76944876},{"color": "#19c74f", "label": "forEachAsync", "x": 378.59113, "y": -684.2996, "attributes": {}, "id": "forEachAsync", "size": 0.4651538},{"color": "#c71969", "label": "noflo", "x": 310.00107, "y": -971.328, "attributes": {}, "id": "noflo", "size": 1.4388975}],"edges":[{"sourceID": "backbone", "attributes": {}, "targetID": "underscore", "size": 1},{"sourceID": "grunt", "attributes": {}, "targetID": "coffee-script", "size": 1},{"sourceID": "grunt", "attributes": {}, "targetID": "js-yaml", "size": 1},{"sourceID": "grunt-contrib-less", "attributes": {}, "targetID": "grunt-lib-contrib", "size": 1},{"sourceID": "grunt-contrib-jshint", "attributes": {}, "targetID": "jshint", "size": 1},{"sourceID": "grunt-contrib-uglify", "attributes": {}, "targetID": "uglify-js", "size": 1},{"sourceID": "grunt-contrib-uglify", "attributes": {}, "targetID": "grunt-lib-contrib", "size": 1},{"sourceID": "node-minify", "attributes": {}, "targetID": "uglify-js", "size": 1},{"sourceID": "node-minify", "attributes": {}, "targetID": "sqwish", "size": 1},{"sourceID": "underscorem", "attributes": {}, "targetID": "underscore", "size": 1},{"sourceID": "hubot", "attributes": {}, "targetID": "coffee-script", "size": 1},{"sourceID": "hubot", "attributes": {}, "targetID": "optparse", "size": 1},{"sourceID": "eco", "attributes": {}, "targetID": "coffee-script", "size": 1},{"sourceID": "coffeekup", "attributes": {}, "targetID": "coffee-script", "size": 1},{"sourceID": "hashish", "attributes": {}, "targetID": "traverse", "size": 1},{"sourceID": "netmask", "attributes": {}, "targetID": "coffee-script", "size": 1},{"sourceID": "jshint", "attributes": {}, "targetID": "underscore", "size": 1},{"sourceID": "jshint", "attributes": {}, "targetID": "cli", "size": 1},{"sourceID": "jshint", "attributes": {}, "targetID": "shelljs", "size": 1},{"sourceID": "sk", "attributes": {}, "targetID": "printf", "size": 1},{"sourceID": "argparse", "attributes": {}, "targetID": "underscore", "size": 1},{"sourceID": "swig", "attributes": {}, "targetID": "underscore", "size": 1},{"sourceID": "jqtpl", "attributes": {}, "targetID": "underscore", "size": 1},{"sourceID": "natural", "attributes": {}, "targetID": "underscore", "size": 1},{"sourceID": "natural", "attributes": {}, "targetID": "sylvester", "size": 1},{"sourceID": "coffeecup", "attributes": {}, "targetID": "coffee-script", "size": 1},{"sourceID": "coffeecup", "attributes": {}, "targetID": "uglify-js", "size": 1},{"sourceID": "coffeecup", "attributes": {}, "targetID": "optparse", "size": 1},{"sourceID": "js-yaml", "attributes": {}, "targetID": "argparse", "size": 1},{"sourceID": "postal", "attributes": {}, "targetID": "underscore", "size": 1},{"sourceID": "node-log", "attributes": {}, "targetID": "coffee-script", "size": 1},{"sourceID": "burrito", "attributes": {}, "targetID": "uglify-js", "size": 1},{"sourceID": "burrito", "attributes": {}, "targetID": "traverse", "size": 1},{"sourceID": "JSONPath", "attributes": {}, "targetID": "underscore", "size": 1},{"sourceID": "extended", "attributes": {}, "targetID": "grunt", "size": 1},{"sourceID": "array-extended", "attributes": {}, "targetID": "grunt", "size": 1},{"sourceID": "array-extended", "attributes": {}, "targetID": "grunt-contrib-jshint", "size": 1},{"sourceID": "array-extended", "attributes": {}, "targetID": "grunt-contrib-uglify", "size": 1},{"sourceID": "array-extended", "attributes": {}, "targetID": "extended", "size": 1},{"sourceID": "smoosh", "attributes": {}, "targetID": "uglify-js", "size": 1},{"sourceID": "smoosh", "attributes": {}, "targetID": "jshint", "size": 1},{"sourceID": "smoosh", "attributes": {}, "targetID": "sqwish", "size": 1},{"sourceID": "difflet", "attributes": {}, "targetID": "charm", "size": 1},{"sourceID": "difflet", "attributes": {}, "targetID": "traverse", "size": 1},{"sourceID": "yamljs", "attributes": {}, "targetID": "argparse", "size": 1},{"sourceID": "forEachAsync", "attributes": {}, "targetID": "sequence", "size": 1},{"sourceID": "noflo", "attributes": {}, "targetID": "underscore", "size": 1},{"sourceID": "noflo", "attributes": {}, "targetID": "npmlog", "size": 1},{"sourceID": "noflo", "attributes": {}, "targetID": "coffee-script", "size": 1},{"sourceID": "noflo", "attributes": {}, "targetID": "cli", "size": 1}]}
